neon_mq_connector/__init__.py
neon_mq_connector/config.py
neon_mq_connector/connector.py
neon_mq_connector/consumers/__init__.py
neon_mq_connector/consumers/blocking_consumer.py
neon_mq_connector/consumers/select_consumer.py
neon_mq_connector/utils/__init__.py
neon_mq_connector/utils/client_utils.py
neon_mq_connector/utils/connection_utils.py
neon_mq_connector/utils/consumer_utils.py
neon_mq_connector/utils/network_utils.py
neon_mq_connector/utils/rabbit_utils.py
neon_mq_connector/utils/thread_utils.py
tests/__init__.py
tests/backward_compat_tests.py
tests/test_connector.py
tests/test_consumers.py
tests/test_utils.py
neon_mq_connector-0.10.0.dist-info/LICENSE.md
neon_mq_connector-0.10.0.dist-info/METADATA
neon_mq_connector-0.10.0.dist-info/WHEEL
neon_mq_connector-0.10.0.dist-info/top_level.txt
neon_mq_connector-0.10.0.dist-info/zip-safe
neon_mq_connector-0.10.0.dist-info/RECORD
