Metadata-Version: 2.1
Name: neon-mq-connector
Version: 0.10.0
Summary: MQ Connector for Neon Modules
Home-page: https://github.com/NeonGeckoCom/neon_mq_connector
Author: NeonGecko
Author-email: developers@neon.ai
License: BSD-3-Clause
Classifier: Intended Audience :: Developers
Classifier: Programming Language :: Python :: 3.8
Requires-Python: >=3.8
License-File: LICENSE.md
Requires-Dist: pika~=1.2
Requires-Dist: ovos-config>=0.0.8,~=0.0
Requires-Dist: ovos-utils>=0.0.32,~=0.0
Requires-Dist: pydantic
